noop.cpython-311-darwin.so
sqlite_url/__init__.py
sqlite_url/url0.dylib
sqlite_url/version.py
sqlite_url-0.1.0.dist-info/METADATA
sqlite_url-0.1.0.dist-info/WHEEL
sqlite_url-0.1.0.dist-info/top_level.txt
sqlite_url-0.1.0.dist-info/RECORD
